bio_util/__init__.py
bio_util/bio_util.py
bio_util/shell.py
bio_util-0.0.2.dist-info/DESCRIPTION.rst
bio_util-0.0.2.dist-info/METADATA
bio_util-0.0.2.dist-info/RECORD
bio_util-0.0.2.dist-info/WHEEL
bio_util-0.0.2.dist-info/metadata.json
bio_util-0.0.2.dist-info/top_level.txt
