Metadata-Version: 2.0
Name: bio-util
Version: 0.0.2
Summary: Library of bioinformatics-related utilities
Home-page: https://github.com/vr1087/bio_util
Author: Vinicio Reynoso
Author-email: vr1087@gmail.com
License: MIT license
Keywords: bio_util
Platform: UNKNOWN
Classifier: Development Status :: 2 - Pre-Alpha
Classifier: Intended Audience :: Developers
Classifier: License :: OSI Approved :: MIT License
Classifier: Natural Language :: English
Classifier: Programming Language :: Python :: 2
Classifier: Programming Language :: Python :: 2.7
Classifier: Programming Language :: Python :: 3
Classifier: Programming Language :: Python :: 3.4
Classifier: Programming Language :: Python :: 3.5
Classifier: Programming Language :: Python :: 3.6
Classifier: Programming Language :: Python :: 3.7
Requires-Dist: biopython
Requires-Dist: bcbio-gff
